<annotation>
	<folder>images</folder>
	<filename>6_2.jpg</filename>
	<path>/Users/victor/Documents/waldo/images/6_2.jpg</path>
	<source>
		<database>Unknown</database>
	</source>
	<size>
		<width>558</width>
		<height>744</height>
		<depth>3</depth>
	</size>
	<segmented>0</segmented>
	<object>
		<name>waldo</name>
		<pose>Unspecified</pose>
		<truncated>0</truncated>
		<difficult>0</difficult>
		<bndbox>
			<xmin>288</xmin>
			<ymin>135</ymin>
			<xmax>322</xmax>
			<ymax>182</ymax>
		</bndbox>
	</object>
</annotation>
